epack/__init__.py
epack/_pack_2d.py
epack/py.typed
epack-0.1.1.dist-info/METADATA
epack-0.1.1.dist-info/WHEEL
epack-0.1.1.dist-info/RECORD
