Metadata-Version: 2.3
Name: epack
Version: 0.1.1
Summary: Bin packing
Author: Erik Soma
Author-email: stillusingirc@gmail.com
Requires-Python: >=3.12
Classifier: Programming Language :: Python :: 3
Classifier: Programming Language :: Python :: 3.12
Classifier: Programming Language :: Python :: 3.13
Requires-Dist: emath (>=0,<1)
